turingarena_cli/__init__.py
turingarena_cli/base.py
turingarena_cli/build_version.py
turingarena_cli/cli.py
turingarena_cli/cloud.py
turingarena_cli/command.py
turingarena_cli/common.py
turingarena_cli/evaluation_events.py
turingarena_cli/get.py
turingarena_cli/login.py
turingarena_cli/problem.py
turingarena_cli/search.py
turingarena_cli/submit.py
turingarena_cli/version.py
turingarena-0.0.2.dev841.dist-info/METADATA
turingarena-0.0.2.dev841.dist-info/WHEEL
turingarena-0.0.2.dev841.dist-info/entry_points.txt
turingarena-0.0.2.dev841.dist-info/top_level.txt
turingarena-0.0.2.dev841.dist-info/RECORD
